LICENSE
README.md
setup.py
dom/__init__.py
dom/base_classes.py
dom/components.py
dom/content.py
dom/forms.py
dom/interactive_elements.py
dom/media.py
dom/metadata.py
dom/plain_elements.py
dom/scripts.py
dom/sectioning.py
dom/semantics.py
dom/short.py
dom/svg.py
dom/tables.py
domgen.egg-info/PKG-INFO
domgen.egg-info/SOURCES.txt
domgen.egg-info/dependency_links.txt
domgen.egg-info/top_level.txt