Metadata-Version: 2.1
Name: domgen
Version: 0.4.1a0
Summary: A package for generating HTML and CSS
Home-page: https://github.com/Starwort/domgen
Author: Starwort
Classifier: Programming Language :: Python :: 3
Classifier: License :: OSI Approved :: MIT License
Classifier: Operating System :: OS Independent
Requires-Python: >=3.6
License-File: LICENSE
